smilewebp/Error.py
smilewebp/Webp.py
smilewebp/__init__.py
test/__init__.py
smilewebp-1.0.3.dist-info/LICENSE.txt
smilewebp-1.0.3.dist-info/METADATA
smilewebp-1.0.3.dist-info/WHEEL
smilewebp-1.0.3.dist-info/top_level.txt
smilewebp-1.0.3.dist-info/RECORD
