Metadata-Version: 2.1
Name: smilewebp
Version: 1.0.3
Summary: Webp image library for python3.
Home-page: https://github.com/sitthykun/smilewebp
Author: Sitthykun LY
Author-email: ly.sitthykun@gmail.com
Project-URL: Bug Tracker, https://github.com/sitthykun/smilewebp/issues
Classifier: Programming Language :: Python :: 3
Classifier: License :: OSI Approved :: MIT License
Classifier: Operating System :: OS Independent
Requires-Python: >=3.6
License-File: LICENSE.txt
